pyhalsimplicity-0.1.0.dist-info/METADATA
pyhalsimplicity-0.1.0.dist-info/WHEEL
pyhalsimplicity-0.1.0.dist-info/licenses/LICENSE
pyhalsimplicity/__init__.py
pyhalsimplicity/pyhalsimplicity.cpython-312-x86_64-linux-gnu.so
pyhalsimplicity-0.1.0.dist-info/RECORD
