Metadata-Version: 2.4
Name: pyhalsimplicity
Version: 0.1.0
License-File: LICENSE
Summary: Python bindings and CLI for hal-simplicity via PyO3
Author-email: coremoon <237020170+coremoon@users.noreply.github.com>
Requires-Python: >=3.9
